setup.py
quick_connect.egg-info/PKG-INFO
quick_connect.egg-info/SOURCES.txt
quick_connect.egg-info/dependency_links.txt
quick_connect.egg-info/top_level.txt
quicknet/__init__.py
quicknet/client.py
quicknet/event.py
quicknet/server.py
quicknet/sterilizer.py
quicknet/utils.py
quicknet/worker.py