Metadata-Version: 1.0
Name: quick-connect
Version: 1.3.4
Summary: Sockets don't have to be a pain
Home-page: https://github.com/Zwork101/quick-net
Author: Zwork101
Author-email: zwork101@gmail.com
License: MIT
Platform: UNKNOWN
